codehackscalculator/__init__.py
codehackscalculator-0.1.dist-info/LICENSE.txt
codehackscalculator-0.1.dist-info/METADATA
codehackscalculator-0.1.dist-info/WHEEL
codehackscalculator-0.1.dist-info/top_level.txt
codehackscalculator-0.1.dist-info/RECORD
